Workbook

Sheet 60-Day Roadmap
A1: Date | B1: Day | C1: Study Day # | D1: Aptitude (3:30-4:30pm) | E1: DSA (5:00-6:00pm) | F1: Communication (6:00-6:30pm) | G1: Lesson (6:30-7:30pm) | H1: AI/ML (8:00-10:30pm) | I1: Aptitude ✓ | J1: DSA ✓ | K1: Comm ✓ | L1: Lesson ✓ | M1: AI/ML ✓ | N1: Day % Complete
A2: 13-Aug-2026 | B2: Thu | C2: 1 | D2: Number System – naturals, primes, factors, divisibility rules | E2: Array basics – traversal, indexing, in-place ops | F2: Speak 2 min on a random topic (record & play back) | G2: College syllabus / current coursework module | H2: AI/ML project work – Career Mentor / Interview Prep agent build, or ML concept study (rotate weekly) | I2: Not Started | J2: Not Started | K2: Not Started | L2: Not Started | M2: Not Started | N2: =COUNTIF(I2:M2,"Done")/5 -> 0
A3: 14-Aug-2026 | B3: Fri | C3: 2 | D3: HCF & LCM – prime factorization, word problems | E3: Two-pointer technique – pair sum, sorted array problems | F3: Read a news/tech article aloud, note 5 new words | G3: GitHub / GSSoC — work toward 1 valid PR to approved external repo | H3: AI/ML project work – Career Mentor / Interview Prep agent build, or ML concept study (rotate weekly) | I3: Not Started | J3: Not Started | K3: Not Started | L3: Not Started | M3: Not Started | N3: =COUNTIF(I3:M3,"Done")/5 -> 0
A4: 15-Aug-2026 | B4: Sat | C4: 3 | D4: Divisibility & Remainders – tests, remainder theorem, cyclicity, last digit | E4: Sliding window (fixed size) – max/min subarray of size k | F4: Mock self-intro (60 sec) – refine for interviews | G4: College syllabus / current coursework module | H4: AI/ML project work – Career Mentor / Interview Prep agent build, or ML concept study (rotate weekly) | I4: Not Started | J4: Not Started | K4: Not Started | L4: Not Started | M4: Not Started | N4: =COUNTIF(I4:M4,"Done")/5 -> 0
A5: 16-Aug-2026 | B5: Sun | C5: 4 | D5: REST DAY — no scheduled tasks | E5: REST DAY — no scheduled tasks | F5: REST DAY — no scheduled tasks | G5: REST DAY — no scheduled tasks | H5: REST DAY — no scheduled tasks | I5: Skipped | J5: Skipped | K5: Skipped | L5: Skipped | M5: Skipped | N5: =COUNTIF(I5:M5,"Done")/5 -> 0
A6: 17-Aug-2026 | B6: Mon | C6: 5 | D6: Percentages – conversion, increase/decrease, successive % | E6: Prefix sums – range sum queries, subarray sum = k | F6: Shadow a native-speaker podcast (5 min) for pronunciation | G6: NPTEL (Database Management System) module study | H6: AI/ML project work – Career Mentor / Interview Prep agent build, or ML concept study (rotate weekly) | I6: Not Started | J6: Not Started | K6: Not Started | L6: Not Started | M6: Not Started | N6: =COUNTIF(I6:M6,"Done")/5 -> 0
A7: 18-Aug-2026 | B7: Tue | C7: 6 | D7: Ratio & Proportion – direct/inverse, sharing quantities | E7: Practice: 'Two Sum' + 'Container With Most Water' | F7: Elevator pitch practice – 'Tell me about yourself' (2 min) | G7: College syllabus / current coursework module | H7: AI/ML project work – Career Mentor / Interview Prep agent build, or ML concept study (rotate weekly) | I7: Not Started | J7: Not Started | K7: Not Started | L7: Not Started | M7: Not Started | N7: =COUNTIF(I7:M7,"Done")/5 -> 0
A8: 19-Aug-2026 | B8: Wed | C8: 7 | D8: WEEK 1 TEST – Number System/HCF-LCM/%/Ratio (Target 70%+) | E8: WEEK REVISION – redo Week 1 array problems, note mistakes | F8: Weekly reflection – record a 3-min answer to a common HR question | G8: College syllabus / current coursework module | H8: AI/ML project work – Career Mentor / Interview Prep agent build, or ML concept study (rotate weekly) | I8: Not Started | J8: Not Started | K8: Not Started | L8: Not Started | M8: Not Started | N8: =COUNTIF(I8:M8,"Done")/5 -> 0
A9: 20-Aug-2026 | B9: Thu | C9: 8 | D9: Average – simple, weighted, age, marks, speed | E9: String basics – manipulation, parsing, in-place reversal | F9: Speak 2 min on a random topic (record & play back) | G9: College syllabus / current coursework module | H9: AI/ML project work – Career Mentor / Interview Prep agent build, or ML concept study (rotate weekly) | I9: Not Started | J9: Not Started | K9: Not Started | L9: Not Started | M9: Not Started | N9: =COUNTIF(I9:M9,"Done")/5 -> 0
A10: 21-Aug-2026 | B10: Fri | C10: 9 | D10: Profit & Loss – CP, SP, MP, discount, profit/loss % | E10: Hashing fundamentals – hashmap for frequency counting | F10: Read a news/tech article aloud, note 5 new words | G10: GitHub / GSSoC — work toward 1 valid PR to approved external repo | H10: AI/ML project work – Career Mentor / Interview Prep agent build, or ML concept study (rotate weekly) | I10: Not Started | J10: Not Started | K10: Not Started | L10: Not Started | M10: Not Started | N10: =COUNTIF(I10:M10,"Done")/5 -> 0
A11: 22-Aug-2026 | B11: Sat | C11: 10 | D11: Simple Interest – SI=PRT/100, principal/rate/time/amount | E11: Sliding window on strings – 'Longest Repeating Char Replacement' | F11: Mock self-intro (60 sec) – refine for interviews | G11: College syllabus / current coursework module | H11: AI/ML project work – Career Mentor / Interview Prep agent build, or ML concept study (rotate weekly) | I11: Not Started | J11: Not Started | K11: Not Started | L11: Not Started | M11: Not Started | N11: =COUNTIF(I11:M11,"Done")/5 -> 0
A12: 23-Aug-2026 | B12: Sun | C12: 11 | D12: REST DAY — no scheduled tasks | E12: REST DAY — no scheduled tasks | F12: REST DAY — no scheduled tasks | G12: REST DAY — no scheduled tasks | H12: REST DAY — no scheduled tasks | I12: Skipped | J12: Skipped | K12: Skipped | L12: Skipped | M12: Skipped | N12: =COUNTIF(I12:M12,"Done")/5 -> 0
A13: 24-Aug-2026 | B13: Mon | C13: 12 | D13: Problems on Ages – present/past/future age, age ratios | E13: Hash-based problems – 'Valid Anagram', grouping | F13: Shadow a native-speaker podcast (5 min) for pronunciation | G13: NPTEL (Database Management System) module study | H13: AI/ML project work – Career Mentor / Interview Prep agent build, or ML concept study (rotate weekly) | I13: Not Started | J13: Not Started | K13: Not Started | L13: Not Started | M13: Not Started | N13: =COUNTIF(I13:M13,"Done")/5 -> 0
... A20: 31-Aug-2026 | B20: Mon | C20: 19 | D20: Trains – crossing person/platform, two trains crossing | E20: Monotonic stack – 'Trapping Rain Water' | F20: Shadow a native-speaker podcast (5 min) for pronunciation | G20: NPTEL (Database Management System) module study | H20: AI/ML project work – Career Mentor / Interview Prep agent build, or ML concept study (rotate weekly) | I20: Not Started | J20: Not Started | K20: Not Started | L20: Not Started | M20: Not Started | N20: =COUNTIF(I20:M20,"Done")/5 -> 0
A21: 01-Sep-2026 | B21: Tue | C21: MODEL 1 EXAM | D21: EXAM PREP – revise subject notes/mistake book (aptitude paused) | E21: EXAM PREP – light DSA revision only (30 min max) or skip | F21: Skip / light reading | G21: Exam study block | H21: Exam study block | I21: Skipped | J21: Skipped | K21: Skipped | L21: Skipped | M21: Skipped | N21: =COUNTIF(I21:M21,"Done")/5 -> 0
A22: 02-Sep-2026 | B22: Wed | C22: MODEL 1 EXAM | D22: EXAM PREP – revise subject notes/mistake book (aptitude paused) | E22: EXAM PREP – light DSA revision only (30 min max) or skip | F22: Skip / light reading | G22: Exam study block | H22: Exam study block | I22: Skipped | J22: Skipped | K22: Skipped | L22: Skipped | M22: Skipped | N22: =COUNTIF(I22:M22,"Done")/5 -> 0
A23: 03-Sep-2026 | B23: Thu | C23: MODEL 1 EXAM | D23: EXAM PREP – revise subject notes/mistake book (aptitude paused) | E23: EXAM PREP – light DSA revision only (30 min max) or skip | F23: Skip / light reading | G23: Exam study block | H23: Exam study block | I23: Skipped | J23: Skipped | K23: Skipped | L23: Skipped | M23: Skipped | N23: =COUNTIF(I23:M23,"Done")/5 -> 0
A24: 04-Sep-2026 | B24: Fri | C24: MODEL 1 EXAM | D24: EXAM PREP – revise subject notes/mistake book (aptitude paused) | E24: EXAM PREP – light DSA revision only (30 min max) or skip | F24: Skip / light reading | G24: Exam study block | H24: Exam study block | I24: Skipped | J24: Skipped | K24: Skipped | L24: Skipped | M24: Skipped | N24: =COUNTIF(I24:M24,"Done")/5 -> 0
A25: 05-Sep-2026 | B25: Sat | C25: MODEL 1 EXAM | D25: EXAM PREP – revise subject notes/mistake book (aptitude paused) | E25: EXAM PREP – light DSA revision only (30 min max) or skip | F25: Skip / light reading | G25: Exam study block | H25: Exam study block | I25: Skipped | J25: Skipped | K25: Skipped | L25: Skipped | M25: Skipped | N25: =COUNTIF(I25:M25,"Done")/5 -> 0
A26: 06-Sep-2026 | B26: Sun | C26: MODEL 1 EXAM | D26: REST DAY — no scheduled tasks | E26: REST DAY — no scheduled tasks | F26: REST DAY — no scheduled tasks | G26: REST DAY — no scheduled tasks | H26: REST DAY — no scheduled tasks | I26: Skipped | J26: Skipped | K26: Skipped | L26: Skipped | M26: Skipped | N26: =COUNTIF(I26:M26,"Done")/5 -> 0
A27: 07-Sep-2026 | B27: Mon | C27: MODEL 1 EXAM | D27: EXAM PREP – revise subject notes/mistake book (aptitude paused) | E27: EXAM PREP – light DSA revision only (30 min max) or skip | F27: Skip / light reading | G27: Exam study block | H27: Exam study block | I27: Skipped | J27: Skipped | K27: Skipped | L27: Skipped | M27: Skipped | N27: =COUNTIF(I27:M27,"Done")/5 -> 0
A28: 08-Sep-2026 | B28: Tue | C28: MODEL 1 EXAM | D28: EXAM PREP – revise subject notes/mistake book (aptitude paused) | E28: EXAM PREP – light DSA revision only (30 min max) or skip | F28: Skip / light reading | G28: Exam study block | H28: Exam study block | I28: Skipped | J28: Skipped | K28: Skipped | L28: Skipped | M28: Skipped | N28: =COUNTIF(I28:M28,"Done")/5 -> 0
A29: 09-Sep-2026 | B29: Wed | C29: 20 | D29: Boats & Streams – upstream/downstream, still-water speed | E29: Queue & design problems – queue via two stacks | F29: Elevator pitch practice – 'Tell me about yourself' (2 min) | G29: College syllabus / current coursework module | H29: AI/ML project work – Career Mentor / Interview Prep agent build, or ML concept study (rotate weekly) | I29: Not Started | J29: Not Started | K29: Not Started | L29: Not Started | M29: Not Started | N29: =COUNTIF(I29:M29,"Done")/5 -> 0
A30: 10-Sep-2026 | B30: Thu | C30: 21 | D30: WEEK 3 TEST – TSD+Work+Trains+Boats (30 Qs in 40 min) | E30: WEEK REVISION – redo Week 3 list/stack/queue problems | F30: Weekly reflection – record a 3-min answer to a common HR question | G30: College syllabus / current coursework module | H30: AI/ML project work – Career Mentor / Interview Prep agent build, or ML concept study (rotate weekly) | I30: Not Started | J30: Not Started | K30: Not Started | L30: Not Started | M30: Not Started | N30: =COUNTIF(I30:M30,"Done")/5 -> 0
A31: 11-Sep-2026 | B31: Fri | C31: 22 | D31: Mixtures & Alligation – replacement, weighted avg | E31: Binary tree traversal – pre/in/post-order (recursive & iterative) | F31: Speak 2 min on a random topic (record & play back) | G31: GitHub / GSSoC — work toward 1 valid PR to approved external repo | H31: AI/ML project work – Career Mentor / Interview Prep agent build, or ML concept study (rotate weekly) | I31: Not Started | J31: Not Started | K31: Not Started | L31: Not Started | M31: Not Started | N31: =COUNTIF(I31:M31,"Done")/5 -> 0
A32: 12-Sep-2026 | B32: Sat | C32: 23 | D32: Probability – sample space, events, P(E)=favorable/total | E32: Level order traversal – 'Binary Tree Level Order Traversal' (BFS) | F32: Read a news/tech article aloud, note 5 new words | G32: College syllabus / current coursework module | H32: AI/ML project work – Career Mentor / Interview Prep agent build, or ML concept study (rotate weekly) | I32: Not Started | J32: Not Started | K32: Not Started | L32: Not Started | M32: Not Started | N32: =COUNTIF(I32:M32,"Done")/5 -> 0
A33: 13-Sep-2026 | B33: Sun | C33: 24 | D33: REST DAY — no scheduled tasks | E33: REST DAY — no scheduled tasks | F33: REST DAY — no scheduled tasks | G33: REST DAY — no scheduled tasks | H33: REST DAY — no scheduled tasks | I33: Skipped | J33: Skipped | K33: Skipped | L33: Skipped | M33: Skipped | N33: =COUNTIF(I33:M33,"Done")/5 -> 0
A34: 14-Sep-2026 | B34: Mon | C34: 25 | D34: Combination – nCr = n!/[r!(n-r)!], P vs C | E34: Tree recursion patterns – 'Lowest Common Ancestor' | F34: Group discussion practice topic (write 5 points, argue aloud) | G34: NPTEL (Database Management System) module study | H34: AI/ML project work – Career Mentor / Interview Prep agent build, or ML concept study (rotate weekly) | I34: Not Started | J34: Not Started | K34: Not Started | L34: Not Started | M34: Not Started | N34: =COUNTIF(I34:M34,"Done")/5 -> 0
A35: 15-Sep-2026 | B35: Tue | C35: 26 | D35: Algebra Basics – linear/quadratic equations, identities | E35: Tree design – 'Serialize/Deserialize BST' | F35: Shadow a native-speaker podcast (5 min) for pronunciation | G35: College syllabus / current coursework module | H35: AI/ML project work – Career Mentor / Interview Prep agent build, or ML concept study (rotate weekly) | I35: Not Started | J35: Not Started | K35: Not Started | L35: Not Started | M35: Not Started | N35: =COUNTIF(I35:M35,"Done")/5 -> 0
A36: 16-Sep-2026 | B36: Wed | C36: 27 | D36: Geometry – lines, angles, triangles, quadrilaterals, circles | E36: Tries & Fenwick/segment tree basics | F36: Elevator pitch practice – 'Tell me about yourself' (2 min) | G36: College syllabus / current coursework module | H36: AI/ML project work – Career Mentor / Interview Prep agent build, or ML concept study (rotate weekly) | I36: Not Started | J36: Not Started | K36: Not Started | L36: Not Started | M36: Not Started | N36: =COUNTIF(I36:M36,"Done")/5 -> 0
A37: 17-Sep-2026 | B37: Thu | C37: 28 | D37: Mensuration – area, perimeter, volume, surface area | E37: WEEK REVISION – redo Week 4 tree problems | F37: Weekly reflection – record a 3-min answer to a common HR question | G37: College syllabus / current coursework module | H37: AI/ML project work – Career Mentor / Interview Prep agent build, or ML concept study (rotate weekly) | I37: Not Started | J37: Not Started | K37: Not Started | L37: Not Started | M37: Not Started | N37: =COUNTIF(I37:M37,"Done")/5 -> 0
A38: 18-Sep-2026 | B38: Fri | C38: 29 | D38: Data Interpretation – tables, bar/pie/line graphs | E38: Graph representation – adjacency list/matrix, DFS basics | F38: Speak 2 min on a random topic (record & play back) | G38: GitHub / GSSoC — work toward 1 valid PR to approved external repo | H38: AI/ML project work – Career Mentor / Interview Prep agent build, or ML concept study (rotate weekly) | I38: Not Started | J38: Not Started | K38: Not Started | L38: Not Started | M38: Not Started | N38: =COUNTIF(I38:M38,"Done")/5 -> 0
A39: 19-Sep-2026 | B39: Sat | C39: 30 | D39: QUANT FULL TEST – Mixed Days 1-29 (60 min, log score/accuracy) | E39: BFS traversal – 'Number of Islands' (grid BFS) | F39: Read a news/tech article aloud, note 5 new words | G39: College syllabus / current coursework module | H39: AI/ML project work – Career Mentor / Interview Prep agent build, or ML concept study (rotate weekly) | I39: Not Started | J39: Not Started | K39: Not Started | L39: Not Started | M39: Not Started | N39: =COUNTIF(I39:M39,"Done")/5 -> 0
A40: 20-Sep-2026 | B40: Sun | C40: 31 | D40: REST DAY — no scheduled tasks | E40: REST DAY — no scheduled tasks | F40: REST DAY — no scheduled tasks | G40: REST DAY — no scheduled tasks | H40: REST DAY — no scheduled tasks | I40: Skipped | J40: Skipped | K40: Skipped | L40: Skipped | M40: Skipped | N40: =COUNTIF(I40:M40,"Done")/5 -> 0
... A54: 04-Oct-2026 | B54: Sun | C54: 45 | D54: REST DAY — no scheduled tasks | E54: REST DAY — no scheduled tasks | F54: REST DAY — no scheduled tasks | G54: REST DAY — no scheduled tasks | H54: REST DAY — no scheduled tasks | I54: Skipped | J54: Skipped | K54: Skipped | L54: Skipped | M54: Skipped | N54: =COUNTIF(I54:M54,"Done")/5 -> 0
A55: 05-Oct-2026 | B55: Mon | C55: MODEL 2 EXAM | D55: EXAM PREP – revise subject notes/mistake book (aptitude paused) | E55: EXAM PREP – light DSA revision only (30 min max) or skip | F55: Skip / light reading | G55: Exam study block | H55: Exam study block | I55: Skipped | J55: Skipped | K55: Skipped | L55: Skipped | M55: Skipped | N55: =COUNTIF(I55:M55,"Done")/5 -> 0
A56: 06-Oct-2026 | B56: Tue | C56: MODEL 2 EXAM | D56: EXAM PREP – revise subject notes/mistake book (aptitude paused) | E56: EXAM PREP – light DSA revision only (30 min max) or skip | F56: Skip / light reading | G56: Exam study block | H56: Exam study block | I56: Skipped | J56: Skipped | K56: Skipped | L56: Skipped | M56: Skipped | N56: =COUNTIF(I56:M56,"Done")/5 -> 0
A57: 07-Oct-2026 | B57: Wed | C57: MODEL 2 EXAM | D57: EXAM PREP – revise subject notes/mistake book (aptitude paused) | E57: EXAM PREP – light DSA revision only (30 min max) or skip | F57: Skip / light reading | G57: Exam study block | H57: Exam study block | I57: Skipped | J57: Skipped | K57: Skipped | L57: Skipped | M57: Skipped | N57: =COUNTIF(I57:M57,"Done")/5 -> 0
A58: 08-Oct-2026 | B58: Thu | C58: MODEL 2 EXAM | D58: EXAM PREP – revise subject notes/mistake book (aptitude paused) | E58: EXAM PREP – light DSA revision only (30 min max) or skip | F58: Skip / light reading | G58: Exam study block | H58: Exam study block | I58: Skipped | J58: Skipped | K58: Skipped | L58: Skipped | M58: Skipped | N58: =COUNTIF(I58:M58,"Done")/5 -> 0
A59: 09-Oct-2026 | B59: Fri | C59: MODEL 2 EXAM | D59: EXAM PREP – revise subject notes/mistake book (aptitude paused) | E59: EXAM PREP – light DSA revision only (30 min max) or skip | F59: Skip / light reading | G59: Exam study block | H59: Exam study block | I59: Skipped | J59: Skipped | K59: Skipped | L59: Skipped | M59: Skipped | N59: =COUNTIF(I59:M59,"Done")/5 -> 0
A60: 10-Oct-2026 | B60: Sat | C60: MODEL 2 EXAM | D60: EXAM PREP – revise subject notes/mistake book (aptitude paused) | E60: EXAM PREP – light DSA revision only (30 min max) or skip | F60: Skip / light reading | G60: Exam study block | H60: Exam study block | I60: Skipped | J60: Skipped | K60: Skipped | L60: Skipped | M60: Skipped | N60: =COUNTIF(I60:M60,"Done")/5 -> 0
A61: 11-Oct-2026 | B61: Sun | C61: MODEL 2 EXAM | D61: REST DAY — no scheduled tasks | E61: REST DAY — no scheduled tasks | F61: REST DAY — no scheduled tasks | G61: REST DAY — no scheduled tasks | H61: REST DAY — no scheduled tasks | I61: Skipped | J61: Skipped | K61: Skipped | L61: Skipped | M61: Skipped | N61: =COUNTIF(I61:M61,"Done")/5 -> 0
A62: 12-Oct-2026 | B62: Mon | C62: MODEL 2 EXAM | D62: EXAM PREP – revise subject notes/mistake book (aptitude paused) | E62: EXAM PREP – light DSA revision only (30 min max) or skip | F62: Skip / light reading | G62: Exam study block | H62: Exam study block | I62: Skipped | J62: Skipped | K62: Skipped | L62: Skipped | M62: Skipped | N62: =COUNTIF(I62:M62,"Done")/5 -> 0
A63: 13-Oct-2026 | B63: Tue | C63: MODEL 2 EXAM | D63: EXAM PREP – revise subject notes/mistake book (aptitude paused) | E63: EXAM PREP – light DSA revision only (30 min max) or skip | F63: Skip / light reading | G63: Exam study block | H63: Exam study block | I63: Skipped | J63: Skipped | K63: Skipped | L63: Skipped | M63: Skipped | N63: =COUNTIF(I63:M63,"Done")/5 -> 0
A64: 14-Oct-2026 | B64: Wed | C64: 46 | D64: Tenses – present/past/future/perfect/continuous, error detection | E64: Grid DP – unique paths, min path sum | F64: Group discussion practice topic (write 5 points, argue aloud) | G64: College syllabus / current coursework module | H64: AI/ML project work – Career Mentor / Interview Prep agent build, or ML concept study (rotate weekly) | I64: Not Started | J64: Not Started | K64: Not Started | L64: Not Started | M64: Not Started | N64: =COUNTIF(I64:M64,"Done")/5 -> 0
A65: 15-Oct-2026 | B65: Thu | C65: 47 | D65: Subject-Verb Agreement – singular/plural rules (20 Qs) | E65: Heap+DP – 'Median in a Stream' | F65: Shadow a native-speaker podcast (5 min) for pronunciation | G65: College syllabus / current coursework module | H65: AI/ML project work – Career Mentor / Interview Prep agent build, or ML concept study (rotate weekly) | I65: Not Started | J65: Not Started | K65: Not Started | L65: Not Started | M65: Not Started | N65: =COUNTIF(I65:M65,"Done")/5 -> 0
A66: 16-Oct-2026 | B66: Fri | C66: 48 | D66: Articles & Prepositions – a/an/the, in/on/at/by/for/from | E66: Greedy – 'Interval Scheduling', 'Gas Station' | F66: Elevator pitch practice – 'Tell me about yourself' (2 min) | G66: GitHub / GSSoC — work toward 1 valid PR to approved external repo | H66: AI/ML project work – Career Mentor / Interview Prep agent build, or ML concept study (rotate weekly) | I66: Not Started | J66: Not Started | K66: Not Started | L66: Not Started | M66: Not Started | N66: =COUNTIF(I66:M66,"Done")/5 -> 0
A67: 17-Oct-2026 | B67: Sat | C67: 49 | D67: Sentence Correction – grammar errors, word usage, structure | E67: WEEK REVISION – redo Week 7 DP/greedy problems | F67: Weekly reflection – record a 3-min answer to a common HR question | G67: College syllabus / current coursework module | H67: AI/ML project work – Career Mentor / Interview Prep agent build, or ML concept study (rotate weekly) | I67: Not Started | J67: Not Started | K67: Not Started | L67: Not Started | M67: Not Started | N67: =COUNTIF(I67:M67,"Done")/5 -> 0
A68: 18-Oct-2026 | B68: Sun | C68: 50 | D68: REST DAY — no scheduled tasks | E68: REST DAY — no scheduled tasks | F68: REST DAY — no scheduled tasks | G68: REST DAY — no scheduled tasks | H68: REST DAY — no scheduled tasks | I68: Skipped | J68: Skipped | K68: Skipped | L68: Skipped | M68: Skipped | N68: =COUNTIF(I68:M68,"Done")/5 -> 0
A69: 19-Oct-2026 | B69: Mon | C69: 51 | D69: Reading Comprehension – main idea, inference, tone (2-3 passages) | E69: Re-solve 2-3 missed Week 3-4 problems | F69: Read a news/tech article aloud, note 5 new words | G69: NPTEL (Database Management System) module study | H69: AI/ML project work – Career Mentor / Interview Prep agent build, or ML concept study (rotate weekly) | I69: Not Started | J69: Not Started | K69: Not Started | L69: Not Started | M69: Not Started | N69: =COUNTIF(I69:M69,"Done")/5 -> 0
A70: 20-Oct-2026 | B70: Tue | C70: 52 | D70: VERBAL TEST – Grammar/Vocab/Correction/RC | E70: Re-solve 2-3 missed Week 5-6 problems | F70: Mock self-intro (60 sec) – refine for interviews | G70: College syllabus / current coursework module | H70: AI/ML project work – Career Mentor / Interview Prep agent build, or ML concept study (rotate weekly) | I70: Not Started | J70: Not Started | K70: Not Started | L70: Not Started | M70: Not Started | N70: =COUNTIF(I70:M70,"Done")/5 -> 0
A71: 21-Oct-2026 | B71: Wed | C71: 53 | D71: QUANT MOCK 1 – 60 min, calc accuracy = correct/attempted×100 | E71: Re-solve 2-3 missed Week 7 (DP/Greedy) problems | F71: Group discussion practice topic (write 5 points, argue aloud) | G71: College syllabus / current coursework module | H71: AI/ML project work – Career Mentor / Interview Prep agent build, or ML concept study (rotate weekly) | I71: Not Started | J71: Not Started | K71: Not Started | L71: Not Started | M71: Not Started | N71: =COUNTIF(I71:M71,"Done")/5 -> 0
A72: 22-Oct-2026 | B72: Thu | C72: 54 | D72: REASONING MOCK 1 – Series/Coding/Relations/Direction/Syllogism/Puzzles | E72: Timed mock interview 1 (45-60 min, random topic) | F72: Shadow a native-speaker podcast (5 min) for pronunciation | G72: College syllabus / current coursework module | H72: AI/ML project work – Career Mentor / Interview Prep agent build, or ML concept study (rotate weekly) | I72: Not Started | J72: Not Started | K72: Not Started | L72: Not Started | M72: Not Started | N72: =COUNTIF(I72:M72,"Done")/5 -> 0
A73: 23-Oct-2026 | B73: Fri | C73: 55 | D73: VERBAL MOCK – Grammar/Vocab/Error detection/RC | E73: Timed mock interview 2 (45-60 min, random topic) | F73: Elevator pitch practice – 'Tell me about yourself' (2 min) | G73: GitHub / GSSoC — work toward 1 valid PR to approved external repo | H73: AI/ML project work – Career Mentor / Interview Prep agent build, or ML concept study (rotate weekly) | I73: Not Started | J73: Not Started | K73: Not Started | L73: Not Started | M73: Not Started | N73: =COUNTIF(I73:M73,"Done")/5 -> 0
A74: 24-Oct-2026 | B74: Sat | C74: 56 | D74: Quant Weak Areas – revisit mistake book, redo weak topics only | E74: Timed mock interview 3 + review error log | F74: Weekly reflection – record a 3-min answer to a common HR question | G74: College syllabus / current coursework module | H74: AI/ML project work – Career Mentor / Interview Prep agent build, or ML concept study (rotate weekly) | I74: Not Started | J74: Not Started | K74: Not Started | L74: Not Started | M74: Not Started | N74: =COUNTIF(I74:M74,"Done")/5 -> 0
A75: 25-Oct-2026 | B75: Sun | C75: 57 | D75: REST DAY — no scheduled tasks | E75: REST DAY — no scheduled tasks | F75: REST DAY — no scheduled tasks | G75: REST DAY — no scheduled tasks | H75: REST DAY — no scheduled tasks | I75: Skipped | J75: Skipped | K75: Skipped | L75: Skipped | M75: Skipped | N75: =COUNTIF(I75:M75,"Done")/5 -> 0
A76: 26-Oct-2026 | B76: Mon | C76: MODEL 3 EXAM | D76: EXAM PREP – revise subject notes/mistake book (aptitude paused) | E76: EXAM PREP – light DSA revision only (30 min max) or skip | F76: Skip / light reading | G76: Exam study block | H76: Exam study block | I76: Skipped | J76: Skipped | K76: Skipped | L76: Skipped | M76: Skipped | N76: =COUNTIF(I76:M76,"Done")/5 -> 0
A77: 27-Oct-2026 | B77: Tue | C77: MODEL 3 EXAM | D77: EXAM PREP – revise subject notes/mistake book (aptitude paused) | E77: EXAM PREP – light DSA revision only (30 min max) or skip | F77: Skip / light reading | G77: Exam study block | H77: Exam study block | I77: Skipped | J77: Skipped | K77: Skipped | L77: Skipped | M77: Skipped | N77: =COUNTIF(I77:M77,"Done")/5 -> 0
A78: 28-Oct-2026 | B78: Wed | C78: MODEL 3 EXAM | D78: EXAM PREP – revise subject notes/mistake book (aptitude paused) | E78: EXAM PREP – light DSA revision only (30 min max) or skip | F78: Skip / light reading | G78: Exam study block | H78: Exam study block | I78: Skipped | J78: Skipped | K78: Skipped | L78: Skipped | M78: Skipped | N78: =COUNTIF(I78:M78,"Done")/5 -> 0
A79: 29-Oct-2026 | B79: Thu | C79: MODEL 3 EXAM | D79: EXAM PREP – revise subject notes/mistake book (aptitude paused) | E79: EXAM PREP – light DSA revision only (30 min max) or skip | F79: Skip / light reading | G79: Exam study block | H79: Exam study block | I79: Skipped | J79: Skipped | K79: Skipped | L79: Skipped | M79: Skipped | N79: =COUNTIF(I79:M79,"Done")/5 -> 0
A80: 30-Oct-2026 | B80: Fri | C80: MODEL 3 EXAM | D80: EXAM PREP – revise subject notes/mistake book (aptitude paused) | E80: EXAM PREP – light DSA revision only (30 min max) or skip | F80: Skip / light reading | G80: Exam study block | H80: Exam study block | I80: Skipped | J80: Skipped | K80: Skipped | L80: Skipped | M80: Skipped | N80: =COUNTIF(I80:M80,"Done")/5 -> 0
A81: 31-Oct-2026 | B81: Sat | C81: MODEL 3 EXAM | D81: EXAM PREP – revise subject notes/mistake book (aptitude paused) | E81: EXAM PREP – light DSA revision only (30 min max) or skip | F81: Skip / light reading | G81: Exam study block | H81: Exam study block | I81: Skipped | J81: Skipped | K81: Skipped | L81: Skipped | M81: Skipped | N81: =COUNTIF(I81:M81,"Done")/5 -> 0
A82: 01-Nov-2026 | B82: Sun | C82: MODEL 3 EXAM | D82: REST DAY — no scheduled tasks | E82: REST DAY — no scheduled tasks | F82: REST DAY — no scheduled tasks | G82: REST DAY — no scheduled tasks | H82: REST DAY — no scheduled tasks | I82: Skipped | J82: Skipped | K82: Skipped | L82: Skipped | M82: Skipped | N82: =COUNTIF(I82:M82,"Done")/5 -> 0
A83: 02-Nov-2026 | B83: Mon | C83: MODEL 3 EXAM | D83: EXAM PREP – revise subject notes/mistake book (aptitude paused) | E83: EXAM PREP – light DSA revision only (30 min max) or skip | F83: Skip / light reading | G83: Exam study block | H83: Exam study block | I83: Skipped | J83: Skipped | K83: Skipped | L83: Skipped | M83: Skipped | N83: =COUNTIF(I83:M83,"Done")/5 -> 0
A84: 03-Nov-2026 | B84: Tue | C84: MODEL 3 EXAM | D84: EXAM PREP – revise subject notes/mistake book (aptitude paused) | E84: EXAM PREP – light DSA revision only (30 min max) or skip | F84: Skip / light reading | G84: Exam study block | H84: Exam study block | I84: Skipped | J84: Skipped | K84: Skipped | L84: Skipped | M84: Skipped | N84: =COUNTIF(I84:M84,"Done")/5 -> 0
A85: 04-Nov-2026 | B85: Wed | C85: 58 | D85: FULL PLACEMENT MOCK – 20 Quant+20 Reasoning+20 Verbal, 60 min | E85: Company focus: Amazon patterns – hash tables + sliding window mix | F85: Read a news/tech article aloud, note 5 new words | G85: College syllabus / current coursework module | H85: AI/ML project work – Career Mentor / Interview Prep agent build, or ML concept study (rotate weekly) | I85: Not Started | J85: Not Started | K85: Not Started | L85: Not Started | M85: Not Started | N85: =COUNTIF(I85:M85,"Done")/5 -> 0
A86: 05-Nov-2026 | B86: Thu | C86: 59 | D86: Mistake Book Revision – formulas, shortcuts, repeated errors | E86: Company focus: Meta patterns – sliding window + design problems | F86: Mock self-intro (60 sec) – refine for interviews | G86: College syllabus / current coursework module | H86: AI/ML project work – Career Mentor / Interview Prep agent build, or ML concept study (rotate weekly) | I86: Not Started | J86: Not Started | K86: Not Started | L86: Not Started | M86: Not Started | N86: =COUNTIF(I86:M86,"Done")/5 -> 0
A87: 06-Nov-2026 | B87: Fri | C87: 60 | D87: FINAL GRAND TEST – full placement aptitude test + result log | E87: Company focus: Flipkart/Zomato patterns – grid BFS + hashing (India-focused) | F87: Group discussion practice topic (write 5 points, argue aloud) | G87: GitHub / GSSoC — work toward 1 valid PR to approved external repo | H87: AI/ML project work – Career Mentor / Interview Prep agent build, or ML concept study (rotate weekly) | I87: Not Started | J87: Not Started | K87: Not Started | L87: Not Started | M87: Not Started | N87: =COUNTIF(I87:M87,"Done")/5 -> 0

Sheet Progress Dashboard
A1: PLACEMENT PREP – PROGRESS DASHBOARD
A2: All figures below update automatically from the '60-Day Roadmap' sheet.
A4: Subject | B4: Done | C4: In Progress | D4: Not Started | E4: Completion %
A5: Aptitude | B5: =COUNTIF('60-Day Roadmap'!I2:I87,"Done") -> 0 | C5: =COUNTIF('60-Day Roadmap'!I2:I87,"In Progress") -> 0 | D5: =COUNTIF('60-Day Roadmap'!I2:I87,"Not Started") -> 51 | E5: =IF((COUNTIF('60-Day Roadmap'!I2:I87,"Done")+COUNTIF('60-Day Roadmap'!I2:I87,"In Progress")+COUNTIF('60-Day Roadmap'!I2:I87,"Not Started"))=0,0,B5/(COUNTIF('60-Day Roadmap'!I2:I87,"Done")+COUNTIF('60-Day Roadmap'!I2:I87,"In Progress")+COUNTIF('60-Day Roadmap'!I2:I87,"Not Started"))) -> 0
A6: DSA | B6: =COUNTIF('60-Day Roadmap'!J2:J87,"Done") -> 0 | C6: =COUNTIF('60-Day Roadmap'!J2:J87,"In Progress") -> 0 | D6: =COUNTIF('60-Day Roadmap'!J2:J87,"Not Started") -> 51 | E6: =IF((COUNTIF('60-Day Roadmap'!J2:J87,"Done")+COUNTIF('60-Day Roadmap'!J2:J87,"In Progress")+COUNTIF('60-Day Roadmap'!J2:J87,"Not Started"))=0,0,B6/(COUNTIF('60-Day Roadmap'!J2:J87,"Done")+COUNTIF('60-Day Roadmap'!J2:J87,"In Progress")+COUNTIF('60-Day Roadmap'!J2:J87,"Not Started"))) -> 0
A7: Communication | B7: =COUNTIF('60-Day Roadmap'!K2:K87,"Done") -> 0 | C7: =COUNTIF('60-Day Roadmap'!K2:K87,"In Progress") -> 0 | D7: =COUNTIF('60-Day Roadmap'!K2:K87,"Not Started") -> 51 | E7: =IF((COUNTIF('60-Day Roadmap'!K2:K87,"Done")+COUNTIF('60-Day Roadmap'!K2:K87,"In Progress")+COUNTIF('60-Day Roadmap'!K2:K87,"Not Started"))=0,0,B7/(COUNTIF('60-Day Roadmap'!K2:K87,"Done")+COUNTIF('60-Day Roadmap'!K2:K87,"In Progress")+COUNTIF('60-Day Roadmap'!K2:K87,"Not Started"))) -> 0
A8: Lesson | B8: =COUNTIF('60-Day Roadmap'!L2:L87,"Done") -> 0 | C8: =COUNTIF('60-Day Roadmap'!L2:L87,"In Progress") -> 0 | D8: =COUNTIF('60-Day Roadmap'!L2:L87,"Not Started") -> 51 | E8: =IF((COUNTIF('60-Day Roadmap'!L2:L87,"Done")+COUNTIF('60-Day Roadmap'!L2:L87,"In Progress")+COUNTIF('60-Day Roadmap'!L2:L87,"Not Started"))=0,0,B8/(COUNTIF('60-Day Roadmap'!L2:L87,"Done")+COUNTIF('60-Day Roadmap'!L2:L87,"In Progress")+COUNTIF('60-Day Roadmap'!L2:L87,"Not Started"))) -> 0
A9: AI/ML | B9: =COUNTIF('60-Day Roadmap'!M2:M87,"Done") -> 0 | C9: =COUNTIF('60-Day Roadmap'!M2:M87,"In Progress") -> 0 | D9: =COUNTIF('60-Day Roadmap'!M2:M87,"Not Started") -> 51 | E9: =IF((COUNTIF('60-Day Roadmap'!M2:M87,"Done")+COUNTIF('60-Day Roadmap'!M2:M87,"In Progress")+COUNTIF('60-Day Roadmap'!M2:M87,"Not Started"))=0,0,B9/(COUNTIF('60-Day Roadmap'!M2:M87,"Done")+COUNTIF('60-Day Roadmap'!M2:M87,"In Progress")+COUNTIF('60-Day Roadmap'!M2:M87,"Not Started"))) -> 0
A11: OVERALL | B11: =SUM(B5:B9) -> 0 | C11: =SUM(C5:C9) -> 0 | D11: =SUM(D5:D9) -> 255 | E11: =IF((B11+C11+D11)=0,0,B11/(B11+C11+D11)) -> 0
A14: Study days fully completed (Day %=100%) | B14: =COUNTIF('60-Day Roadmap'!N2:N87,1) -> 0
A15: Total study days in plan | B15: =COUNTIF('60-Day Roadmap'!C2:C87,">0") -> 60
A16: Exam blackout days (auto-marked Skipped) | B16: =COUNTIF('60-Day Roadmap'!I2:I87,"Skipped") -> 35
A17: Overall plan completion | B17: =AVERAGE('60-Day Roadmap'!N2:N87) -> 0
A20: HOW TO TRACK: Each day, open the '60-Day Roadmap' sheet and set the 5 status cells (Aptitude/DSA/Comm/Lesson/AI/ML) to Done, In Progress, Not Started, or Skipped via the dropdown. This dashboard and the 'Day % Complete' column update automatically.
A24: TODAY'S FOCUS (auto-updates to today's date)
A25: Today's date | B25: =TEXT(TODAY(),"ddd, dd-mmm-yyyy") -> Wed, 12-Aug-2026
A26: Study Day # | B26: =IFERROR(INDEX('60-Day Roadmap'!C:C,MATCH(TEXT(TODAY(),"dd-mmm-yyyy"),'60-Day Roadmap'!A:A,0)),"No entry for today") -> No entry for today
A27: Day % Complete | B27: =IFERROR(INDEX('60-Day Roadmap'!N:N,MATCH(TEXT(TODAY(),"dd-mmm-yyyy"),'60-Day Roadmap'!A:A,0)),"")
A29: Subject | B29: Task for Today | C29: Status
A30: Aptitude | B30: =IFERROR(INDEX('60-Day Roadmap'!D:D,MATCH(TEXT(TODAY(),"dd-mmm-yyyy"),'60-Day Roadmap'!A:A,0)),"-") -> - | C30: =IFERROR(INDEX('60-Day Roadmap'!I:I,MATCH(TEXT(TODAY(),"dd-mmm-yyyy"),'60-Day Roadmap'!A:A,0)),"-") -> -
A31: DSA | B31: =IFERROR(INDEX('60-Day Roadmap'!E:E,MATCH(TEXT(TODAY(),"dd-mmm-yyyy"),'60-Day Roadmap'!A:A,0)),"-") -> - | C31: =IFERROR(INDEX('60-Day Roadmap'!J:J,MATCH(TEXT(TODAY(),"dd-mmm-yyyy"),'60-Day Roadmap'!A:A,0)),"-") -> -
A32: Communication | B32: =IFERROR(INDEX('60-Day Roadmap'!F:F,MATCH(TEXT(TODAY(),"dd-mmm-yyyy"),'60-Day Roadmap'!A:A,0)),"-") -> - | C32: =IFERROR(INDEX('60-Day Roadmap'!K:K,MATCH(TEXT(TODAY(),"dd-mmm-yyyy"),'60-Day Roadmap'!A:A,0)),"-") -> -
A33: Lesson | B33: =IFERROR(INDEX('60-Day Roadmap'!G:G,MATCH(TEXT(TODAY(),"dd-mmm-yyyy"),'60-Day Roadmap'!A:A,0)),"-") -> - | C33: =IFERROR(INDEX('60-Day Roadmap'!L:L,MATCH(TEXT(TODAY(),"dd-mmm-yyyy"),'60-Day Roadmap'!A:A,0)),"-") -> -
A34: AI/ML | B34: =IFERROR(INDEX('60-Day Roadmap'!H:H,MATCH(TEXT(TODAY(),"dd-mmm-yyyy"),'60-Day Roadmap'!A:A,0)),"-") -> - | C34: =IFERROR(INDEX('60-Day Roadmap'!M:M,MATCH(TEXT(TODAY(),"dd-mmm-yyyy"),'60-Day Roadmap'!A:A,0)),"-") -> -
A36: Tip: To mark today's tasks Done, go to the '60-Day Roadmap' sheet, find today's row, and update the ✓ status columns (I-M) — this section updates automatically.

Sheet Summary & Notes
A1: PLACEMENT PREP ROADMAP – SUMMARY
A2: RULE: On any day I have a college exam, I only prepare for that exam that day — skip Aptitude/DSA/Comm/Lesson/AI/ML for that day and mark those 5 status cells 'Skipped' in the 60-Day Roadmap.
A3: Start date: 13-Aug-2026 | End date: 11-Oct-2026
A4: Total study days: 60 (Aptitude + DSA + Communication + Lesson + AI/ML)
A5: Total calendar span includes 3 exam blackout periods where daily plan pauses:
A6: • Model 1: 29 Aug – 5 Sep 2026 (8 days)
A7: • Model 2: 2 Oct – 10 Oct 2026 (9 days)
A8: • Model 3: 23 Oct – 31 Oct 2026 (9 days)
A9: On exam days, the daily plan is replaced with exam revision — the 60 study days resume right after each exam ends, so you still get the full 60 days of placement prep.
A10: REST RULE: Sundays are fully free — no scheduled tasks. All weekend-only prep items (competition, SIH/IEEE, GATE, language, PEP/HOPE) now sit on Saturday only.
A11: HOW TO USE
A12: • Aptitude column follows a fixed 60-day topic sequence (Number System → Final Grand Test), matching your Executive_Summary/Aptitude source.
... A18: Good luck — solve the right question quickly and accurately, not just more questions.

Sheet Placement Parameters
A1: # | B1: Parameter | C1: Target / Threshold | D1: Max Marks | E1: Where it fits in roadmap | F1: Status | G1: Marks Achieved | H1: Notes
A2: 1 | B2: Coding volume: 1000+ problems (Skillrack/LeetCode/HackerRank) + 75 SQL | C2: 1000 problems + 75 SQL | D2: 25 | E2: DSA block (5-6pm) daily, weekend SQL push | F2: Not Started
A3: 2 | B3: 1 valid PR to approved external repo (GitHub/GSSoC) | C3: 1 merged/approved PR | D3: 3 | E3: Tue Lesson block (6:30-7:30pm) | F3: Not Started
A4: 3 | B4: Competition assessment | C4: Pass/Completed | D4: 2 | E4: Sat afternoon block (1:00-2:00pm) | F4: Not Started
A5: 4 | B5: NPTEL (DBMS) or International cert (Oracle/Cisco/Salesforce/MongoDB/Databricks) | C5: Elite/Silver/Gold or Foundation/Associate/Professional | D5: 15 | E5: Fri Lesson block (6:30-7:30pm) | F5: Not Started
A6: 5 | B6: CodeChef rating | C6: 2★=5, 3★=10, 4★=15 | D6: 15 | E6: Thu Lesson block (6:30-7:30pm) | F6: Not Started
A7: 6 | B7: SIH / IEEE paper / patent / conference | C7: SIH(3) to Granted patent(20) | D7: 20 | E7: Sat afternoon block (2:00-3:30pm) | F7: Not Started
A8: 7 | B8: Aptitude score + Communication (Linguaskill) | C8: 60-69=6 ... 90+=15; Comm 3-5 | D8: 15 | E8: Daily Aptitude (3:30-4:30) + Comm (6-6:30) | F8: Not Started
A9: 8 | B9: HackerRank Monthly Test | C9: Confirm marks with placement cell | D9: 0 | E9: Not yet scheduled | F9: Not Started
A10: 9 | B10: GATE appearance | C10: Register by 21 Sept (Rs.1000) | D10: 15 | E10: Sat block (3:30-4:00pm) — registration check | F10: Not Started
A11: 10 | B11: Internship / PPO-PPI offer | C11: Offer(10) / Completed(15) / PPO-PPI(20) | D11: 20 | E11: Ongoing — apply during weekdays as opportunities arise | F11: Not Started
A12: 11 | B12: Foreign Language (German/Japanese/French) | C12: A1=7, A2=12, B1=15 | D12: 15 | E12: Sat afternoon block (4:00-5:00pm) | F12: Not Started
A13: 12 | B13: PEP / HOPE Elite | C13: PEP(5) / HOPE Elite(15) | D13: 15 | E13: Sat afternoon block (5:00-6:00pm) | F13: Not Started
B14: TOTAL | D14: =SUM(D2:D13) -> 160 | G14: =SUM(G2:G13) -> 0

Sheet Research Paper Tracker
A1: Week | B1: Dates | C1: Paper 1 Milestone | D1: Paper 2 Milestone | E1: Weekend Slot Used | F1: Status P1 | G1: Status P2
A2: Wk 1 | B2: 15-16 Aug | C2: Finalize topic + start literature review | D2: Finalize topic + start literature review | E2: Sat AM + Sun AM | F2: Not Started | G2: Not Started
A3: Wk 2 | B3: 22-23 Aug | C3: Complete literature review, outline | D3: Complete literature review, outline | E3: Sat AM + Sun AM | F3: Not Started | G3: Not Started
A4: Wk 3 | B4: (Model 1 Exam 29 Aug-5 Sept — pause) | C4: Exam blackout — no paper work | D4: Exam blackout — no paper work | E4: — | F4: Not Started | G4: Not Started
A5: Wk 4 | B5: 6-7 Sept | C5: Draft full paper (methodology + results) | D5: Outline + start draft | E5: Sat AM + Sun AM | F5: Not Started | G5: Not Started
A6: Wk 5 | B6: 13-14 Sept | C6: Finish draft, send to guide/co-author | D6: Continue drafting | E6: Sat AM + Sun AM | F6: Not Started | G6: Not Started
A7: Wk 6 | B7: 20-21 Sept | C7: Revise per feedback, format for submission | D7: Finish draft, send to guide/co-author | E7: Sat AM + Sun AM | F7: Not Started | G7: Not Started
A8: Wk 7 | B8: 27-28 Sept | C8: SUBMIT Paper 1 | D8: Revise + format + SUBMIT Paper 2 | E8: Sat AM + Sun AM | F8: Not Started | G8: Not Started
